README.rst
setup.py
epages/__init__.py
epages/auth.py
epages/client.py
epages/error.py
epages_rest_python.egg-info/PKG-INFO
epages_rest_python.egg-info/SOURCES.txt
epages_rest_python.egg-info/dependency_links.txt
epages_rest_python.egg-info/requires.txt
epages_rest_python.egg-info/top_level.txt