Metadata-Version: 1.0
Name: epages-rest-python
Version: 0.9.0
Summary: The ePages online shop API for Python
Home-page: https://github.com/ooz/epages-rest-python
Author: Oliver Zscheyge
Author-email: oliverzscheyge@gmail.com
License: MIT
Platform: UNKNOWN
